LingjixianDiwuZhenyan/README.md
LingjixianDiwuZhenyan/__init__.py
LingjixianDiwuZhenyan/__main__.py
LingjixianDiwuZhenyan/file.epub
LingjixianDiwuZhenyan/index.html
LingjixianDiwuZhenyan/css/__init__.py
LingjixianDiwuZhenyan/css/annotations.css
LingjixianDiwuZhenyan/css/main.css
LingjixianDiwuZhenyan/css/normalize.css
LingjixianDiwuZhenyan/css/popup.css
LingjixianDiwuZhenyan/font/__init__.py
LingjixianDiwuZhenyan/font/fontello.eot
LingjixianDiwuZhenyan/font/fontello.svg
LingjixianDiwuZhenyan/font/fontello.ttf
LingjixianDiwuZhenyan/font/fontello.woff
LingjixianDiwuZhenyan/img/__init__.py
LingjixianDiwuZhenyan/img/annotator-glyph-sprite.png
LingjixianDiwuZhenyan/img/annotator-icon-sprite.png
LingjixianDiwuZhenyan/img/apple-touch-icon.png
LingjixianDiwuZhenyan/img/cancelfullscreen.png
LingjixianDiwuZhenyan/img/close.png
LingjixianDiwuZhenyan/img/fullscreen.png
LingjixianDiwuZhenyan/img/loader.gif
LingjixianDiwuZhenyan/img/menu-icon.png
LingjixianDiwuZhenyan/img/save.png
LingjixianDiwuZhenyan/img/saved.png
LingjixianDiwuZhenyan/img/settings-s.png
LingjixianDiwuZhenyan/img/settings.png
LingjixianDiwuZhenyan/img/star.png
LingjixianDiwuZhenyan/js/__init__.py
LingjixianDiwuZhenyan/js/epub.js
LingjixianDiwuZhenyan/js/epub.min.js
LingjixianDiwuZhenyan/js/epub.min.map
LingjixianDiwuZhenyan/js/hooks.min.js
LingjixianDiwuZhenyan/js/hooks.min.map
LingjixianDiwuZhenyan/js/reader.js
LingjixianDiwuZhenyan/js/reader.js.map
LingjixianDiwuZhenyan/js/reader.min.js
LingjixianDiwuZhenyan/js/reader.min.map
LingjixianDiwuZhenyan/js/hooks/__init__.py
LingjixianDiwuZhenyan/js/hooks/extensions/__init__.py
LingjixianDiwuZhenyan/js/hooks/extensions/highlight.js
LingjixianDiwuZhenyan/js/libs/__init__.py
LingjixianDiwuZhenyan/js/libs/jquery.min.js
LingjixianDiwuZhenyan/js/libs/localforage.min.js
LingjixianDiwuZhenyan/js/libs/screenfull.js
LingjixianDiwuZhenyan/js/libs/screenfull.min.js
LingjixianDiwuZhenyan/js/libs/zip.min.js
LingjixianDiwuZhenyan/js/plugins/__init__.py
lingjixian_diwu_zhenyan-2022.9.29.0.dist-info/METADATA
lingjixian_diwu_zhenyan-2022.9.29.0.dist-info/WHEEL
lingjixian_diwu_zhenyan-2022.9.29.0.dist-info/entry_points.txt
lingjixian_diwu_zhenyan-2022.9.29.0.dist-info/top_level.txt
lingjixian_diwu_zhenyan-2022.9.29.0.dist-info/RECORD
